filebase_api/__init__.py
filebase_api/decorators.py
filebase_api/helpers.py
filebase_api/templates.py
filebase_api/templates_test.py
filebase_api/webserver.py
filebase_api/webservice.py
filebase_api-0.1.0.dist-info/METADATA
filebase_api-0.1.0.dist-info/WHEEL
filebase_api-0.1.0.dist-info/top_level.txt
filebase_api-0.1.0.dist-info/RECORD
